LICENSE
MANIFEST.in
README.md
setup.cfg
setup.py
availability/__init__.py
availability/admin.py
availability/managers.py
availability/models.py
availability/querysets.py
availability/translation.py
availability/locale/ru/LC_MESSAGES/django.mo
availability/locale/ru/LC_MESSAGES/django.po
availability/locale/uk/LC_MESSAGES/django.mo
availability/locale/uk/LC_MESSAGES/django.po
availability/migrations/0001_initial.py
availability/migrations/__init__.py
django_mp_availability.egg-info/PKG-INFO
django_mp_availability.egg-info/SOURCES.txt
django_mp_availability.egg-info/dependency_links.txt
django_mp_availability.egg-info/top_level.txt