Metadata-Version: 2.1
Name: django-mp-availability
Version: 0.5.0
Summary: Django availability app
Home-page: https://github.com/pmaigutyak/mp-availability
Author: Paul Maigutyak
Author-email: pmaigutyak@gmail.com
License: MIT
Download-URL: https://github.com/pmaigutyak/mp-availability/archive/0.5.0.tar.gz
Platform: UNKNOWN
License-File: LICENSE
